{
  "project_info": {
    "project_number": "1060954611112",
    "project_id": "k224111488dokhanhlinhpractice",
    "storage_bucket": "k224111488dokhanhlinhpractice.firebasestorage.app"
  },
  "client": [
    {
      "client_info": {
        "mobilesdk_app_id": "1:1060954611112:android:cde670876741ed0e92919d",
        "android_client_info": {
          "package_name": "com.example.k224111488_dokhanhlinh_practice"
        }
      },
      "oauth_client": [],
      "api_key": [
        {
          "current_key": "AIzaSyC0id5H4_KZbVnVGiLSt2nHPkv9BqWlx0s"
        }
      ],
      "services": {
        "appinvite_service": {
          "other_platform_oauth_client": []
        }
      }
    }
  ],
  "configuration_version": "1"
}